uncomment/__init__.py
uncomment/cli.py
uncomment/downloader.py
uncomment-2.10.4.dist-info/METADATA
uncomment-2.10.4.dist-info/WHEEL
uncomment-2.10.4.dist-info/entry_points.txt
uncomment-2.10.4.dist-info/top_level.txt
uncomment-2.10.4.dist-info/RECORD
