Metadata-Version: 2.1
Name: uncomment
Version: 2.10.4
Summary: A fast Rust-based CLI tool for removing comments from source code
Author-email: Na'aman Hirschfeld <nhirschfeld@gmail.com>
License: MIT
Project-URL: Homepage, https://github.com/Goldziher/uncomment
Project-URL: Repository, https://github.com/Goldziher/uncomment.git
Project-URL: Issues, https://github.com/Goldziher/uncomment/issues
Keywords: comments,cli,rust,remove-comments,code-cleanup,ai-generated-code,formatting,uncomment
Classifier: Development Status :: 5 - Production/Stable
Classifier: Intended Audience :: Developers
Classifier: License :: OSI Approved :: MIT License
Classifier: Programming Language :: Python :: 3
Classifier: Programming Language :: Python :: 3.8
Classifier: Programming Language :: Python :: 3.9
Classifier: Programming Language :: Python :: 3.10
Classifier: Programming Language :: Python :: 3.11
Classifier: Programming Language :: Python :: 3.12
Classifier: Topic :: Software Development :: Code Generators
Classifier: Topic :: Text Processing
Classifier: Environment :: Console
Requires-Python: >=3.8
Requires-Dist: certifi>=2024.7.4
